__backup__/__init__.py
__backup__/imagefile.py
__backup__/measurements.py
__backup__/oap.py
__backup__/core_depricated/__init__.py
__backup__/old/sizing.py
__backup__/old/apps/__init__.py
__backup__/old/apps/ccr.py
__backup__/old/apps/mac.py
__backup__/old/apps/pic.py
__backup__/old/apps/setup.py
__backup__/old/deep/__init__.py
__oap_c/core.cp38-win_amd64.pyd
blender/Blender_RotateScaleTransform.py
docs/source/conf.py
oap/__conf__.py
oap/__init__.py
oap/__dev__/__init__.py
oap/__dev__/experimental.py
oap/__dev__/photobooth.py
oap/bnp/__init__.py
oap/bnp/clamp.py
oap/bnp/loading.py
oap/bnp/progress.py
oap/bnp/runtime.py
oap/core/__init__.py
oap/deep/__init__.py
oap/deep/classifier.py
oap/deep/imports.py
oap/deep/models.py
oap/deep/models/final_column_mc_pre14_e11_acc0.98_fs0.98.hdf5
oap/deep/models/final_rosette_mc_pre06_e05_acc0.97_fs0.97.hdf5
oap/lib/__init__.py
oap/lib/imagefile.py
oap/utils/__init__.py
oap/utils/bytes.py
oap/utils/console.py
oap/utils/files.py
oap/utils/sizing.py
tests/data.py
tests/test_all.py
tests/test_utils.py
tests/test_utils_sizing.py
oap-0.0.14.dist-info/LICENSE
oap-0.0.14.dist-info/METADATA
oap-0.0.14.dist-info/WHEEL
oap-0.0.14.dist-info/top_level.txt
oap-0.0.14.dist-info/RECORD
