Metadata-Version: 2.1
Name: oap
Version: 0.0.14
Summary: A transparent library for processing and analyzing individual images of Optical Array Probes (OAPs)
Home-page: https://github.com/lcsgrlch/oap
Author: Lucas Grulich (grulich@uni-mainz.de)
Author-email: lucasgrulich@gmx.de
License: UNKNOWN
Platform: UNKNOWN
Classifier: Programming Language :: Python :: 3
Classifier: License :: OSI Approved :: MIT License
Classifier: Operating System :: OS Independent
Requires-Python: >=3.7
License-File: LICENSE
Requires-Dist: numpy
